gzbus/__init__.py
gzbus/extract.py
gzbus/query.py
gzbus/utils.py
gzbus/data/__init__.py
gzbus/data/gzyyjt.py
gzbus-0.1.1.dist-info/DESCRIPTION.rst
gzbus-0.1.1.dist-info/METADATA
gzbus-0.1.1.dist-info/metadata.json
gzbus-0.1.1.dist-info/RECORD
gzbus-0.1.1.dist-info/top_level.txt
gzbus-0.1.1.dist-info/WHEEL
