Metadata-Version: 2.0
Name: gzbus
Version: 0.1.1
Summary: Guangzhou bus routine realtime tracking.
Home-page: https://github.com/bcho/gzbus
Author: hbc
Author-email: bcxxxxxx@gmail.com
License: MIT
Platform: UNKNOWN
Classifier: Development Status :: 4 - Beta
Classifier: Operating System :: POSIX :: Linux
Classifier: Programming Language :: Python :: 3
Classifier: Programming Language :: Python :: 2
Classifier: Topic :: Software Development :: Libraries :: Python Modules
Classifier: Intended Audience :: Developers
Classifier: License :: OSI Approved :: MIT License
Requires-Dist: lxml
Requires-Dist: pyquery
Requires-Dist: requests
